<?xml version="1.0" encoding="ISO-8859-1"?>
<intern xmlns:fo="http://www.w3.org/1999/XSL/Format">
	<fo:block font-family="Arial" font-size="12pt" language="DE" text-align="justify">
	<fo:inline font-weight="bold">
	<fo:leader leader-length="0pt"/>Ihre Immobilienanfrage</fo:inline>
	</fo:block>
	
	<fo:block font-family="Arial" font-size="12pt" language="DE">
	<fo:inline>
	<fo:leader leader-length="0pt"/></fo:inline>
	</fo:block>
	<fo:block/>
	<fo:block/>
	<fo:block/>
	<fo:block font-family="Arial" font-size="12pt" language="DE">
	<briefanrede/>,</fo:block>

<fo:block font-family="Arial" font-size="12pt" language="DE"><fo:leader/></fo:block>
	<fo:block font-family="Arial" font-size="12pt" language="DE"><fo:inline>
	<fo:leader leader-length="0pt"/>wunschgemäß bieten wir ihnen nachfolgendes Objekt an:</fo:inline></fo:block>
	<fo:block font-family="Arial" font-size="12pt" language="DE"><fo:leader/></fo:block><fo:block id="Objekt"/>
	<fo:block font-family="Arial" font-size="12pt" language="DE"><fo:inline font-weight="bold"><fo:leader leader-length="0pt"></fo:leader>
	<angnr></angnr></fo:inline><fo:inline font-weight="bold"><fo:leader leader-length="0pt"/>, </fo:inline><fo:inline font-weight="bold">
	<fo:leader leader-length="0pt">
</fo:leader><kurzbeschreibung></kurzbeschreibung></fo:inline><fo:inline font-weight="bold">
<fo:leader leader-length="0pt"/>,  </fo:inline><fo:inline font-weight="bold"><fo:leader leader-length="0pt">
	<lagebeschreibung></lagebeschreibung></fo:leader><lagebeschreibung></lagebeschreibung></fo:inline><fo:inline><fo:block/>
	</fo:inline></fo:block><fo:block font-family="Arial" font-size="12pt" language="DE" text-align="right"><fo:leader/></fo:block>
	<fo:block font-family="Arial" font-size="12pt" language="DE"><fo:inline>
	<fo:leader leader-length="0pt"/>Alles Nähere ersehen Sie aus beiliegenden Erläuterungen.</fo:inline>
	</fo:block>
	<fo:block font-family="Arial" font-size="12pt" language="DE"><fo:leader/></fo:block>

<fo:block font-family="Arial" font-size="12pt" language="DE"><fo:inline>
	<fo:leader leader-length="0pt"/>Gebühren vor Vertragsabschluß erheben wir nicht. Erst wenn in Folge unserer Tätigkeit ein Abschluß zustande kommt, ist von Ihnen die aus dem Exposee ersichtliche Provision zu zahlen.</fo:inline></fo:block>
	<fo:block font-family="Arial" font-size="12pt" language="DE"><fo:leader/></fo:block>

	<fo:block font-family="Arial" font-size="12pt" language="DE"><fo:inline>
	<fo:leader leader-length="0pt"/>Mit ausführlichen Unterlagen, zur Beantwortung von Fragen sowie zu einer Be-</fo:inline></fo:block>
	<fo:block font-family="Arial" font-size="12pt" language="DE"><fo:inline>
	<fo:leader leader-length="0pt"/>sichtigung stehen wir Ihnen jederzeit zur Verfügung.</fo:inline></fo:block>
	<fo:block font-family="Arial" font-size="12pt" language="DE"><fo:leader/></fo:block>
	<fo:block font-family="Arial" font-size="12pt" language="DE"><fo:inline>
	<fo:leader leader-length="0pt"/>Versäumen Sie bitte nie, uns ein Gegengebot abzugeben, wenn Ihnen ein Preis</fo:inline>
	</fo:block><fo:block font-family="Arial" font-size="12pt" language="DE"><fo:inline>
	<fo:leader leader-length="0pt"/>zu hoch erscheint. Es ist eine unserer Aufgaben, für Sie zu verhandeln.</fo:inline></fo:block>
	<fo:block font-family="Arial" font-size="12pt" language="DE"><fo:leader/>
	</fo:block>
		</intern>
